Workbook

Sheet Products
A1: product_id | B1: category | C1: sub_category | D1: product_name | E1: unit_price | F1: unit_cost
A2: PROD0001 | B2: Electronics | C2: Headphones | D2: Headphones - Variant 1 | E2: 4105.51 | F2: 2579.98
A3: PROD0002 | B3: Electronics | C3: Headphones | D3: Headphones - Variant 2 | E3: 3877.46 | F3: 2229.92
A4: PROD0003 | B4: Electronics | C4: Headphones | D4: Headphones - Variant 3 | E4: 3976.47 | F4: 2375.49
A5: PROD0004 | B5: Electronics | C5: Smartwatch | D5: Smartwatch - Variant 1 | E5: 3547.27 | F5: 2352.39
A6: PROD0005 | B6: Electronics | C6: Smartwatch | D6: Smartwatch - Variant 2 | E6: 4680.15 | F6: 2936.63
A7: PROD0006 | B7: Electronics | C7: Smartwatch | D7: Smartwatch - Variant 3 | E7: 796.74 | F7: 441.26
A8: PROD0007 | B8: Electronics | C8: Bluetooth Speaker | D8: Bluetooth Speaker - Variant 1 | E8: 4219.86 | F8: 2763.79
A9: PROD0008 | B9: Electronics | C9: Bluetooth Speaker | D9: Bluetooth Speaker - Variant 2 | E9: 3987.6 | F9: 2380.14
A10: PROD0009 | B10: Electronics | C10: Bluetooth Speaker | D10: Bluetooth Speaker - Variant 3 | E10: 2051.88 | F10: 1140.89
A11: PROD0010 | B11: Electronics | C11: Power Bank | D11: Power Bank - Variant 1 | E11: 4825.72 | F11: 3298.73
A12: PROD0011 | B12: Electronics | C12: Power Bank | D12: Power Bank - Variant 2 | E12: 4698.42 | F12: 2833.61
A13: PROD0012 | B13: Electronics | C13: Power Bank | D13: Power Bank - Variant 3 | E13: 3250.59 | F13: 2228.93
... A109: PROD0108 | B109: Books & Stationery | C109: Pen Drive | D109: Pen Drive - Variant 3 | E109: 692.57 | F109: 440.26

Sheet Category Analysis
A3: Row Labels | B3: Sum of line_total
A4: Beauty & Personal Care | B4: 1765668.4
A5: Books & Stationery | B5: 846883.51
A6: Electronics | B6: 21879107
A7: Fashion | B7: 5077254.3
A8: Home & Kitchen | B8: 8329660.8
A9: Sports & Fitness | B9: 3515874.5
A10: Grand Total | B10: 41414449

Sheet Return Rate
A3: Row Labels | B3: Average of Returned_flag
A4: Fashion | B4: 0.10653951
A5: Beauty & Personal Care | B5: 0.064102564
A6: Electronics | B6: 0.063105836
A7: Home & Kitchen | B7: 0.062198239
A8: Sports & Fitness | B8: 0.053020134
A9: Books & Stationery | B9: 0.021204411
A10: Grand Total | B10: 0.068641917

Sheet Top Products
A3: Row Labels | B3: Sum of line_total
A4: PROD0014 | B4: 1760941.2
A5: PROD0005 | B5: 1723231.1
A6: PROD0007 | B6: 1625279
A7: PROD0011 | B7: 1577494.8
A8: PROD0010 | B8: 1570530.5
A9: PROD0008 | B9: 1481592.8
A10: PROD0002 | B10: 1470332.7
A11: PROD0018 | B11: 1450987.4
A12: PROD0003 | B12: 1437295.2
A13: PROD0001 | B13: 1435902
A14: Grand Total | B14: 15533587

Sheet Order_Items
A1: order_item_id | B1: order_id | C1: product_id | D1: quantity | E1: discount_pct | F1: line_total | G1: is_returned | H1: Category | I1: Returned_flag
A2: ITEM0000001 | B2: ORD000001 | C2: PROD0090 | D2: 1 | E2: 10 | F2: 1072.86 | G2: FALSE | H2: =VLOOKUP(C2,Products!A:B,2,FALSE) -> Sports & Fitness | I2: =IF(G2=TRUE,1,0) -> 0
A3: ITEM0000002 | B3: ORD000002 | C3: PROD0055 | D3: 1 | E3: 10 | F3: 834.98 | G3: FALSE | H3: =VLOOKUP(C3,Products!A:B,2,FALSE) -> Beauty & Personal Care | I3: =IF(G3=TRUE,1,0) -> 0
A4: ITEM0000003 | B4: ORD000003 | C4: PROD0051 | D4: 1 | E4: 15 | F4: 1203.56 | G4: TRUE | H4: =VLOOKUP(C4,Products!A:B,2,FALSE) -> Fashion | I4: =IF(G4=TRUE,1,0) -> 1
A5: ITEM0000004 | B5: ORD000003 | C5: PROD0016 | D5: 1 | E5: 0 | F5: 1766.27 | G5: FALSE | H5: =VLOOKUP(C5,Products!A:B,2,FALSE) -> Electronics | I5: =IF(G5=TRUE,1,0) -> 0
A6: ITEM0000005 | B6: ORD000003 | C6: PROD0017 | D6: 1 | E6: 10 | F6: 490.75 | G6: FALSE | H6: =VLOOKUP(C6,Products!A:B,2,FALSE) -> Electronics | I6: =IF(G6=TRUE,1,0) -> 0
A7: ITEM0000006 | B7: ORD000004 | C7: PROD0088 | D7: 1 | E7: 0 | F7: 1914.83 | G7: FALSE | H7: =VLOOKUP(C7,Products!A:B,2,FALSE) -> Sports & Fitness | I7: =IF(G7=TRUE,1,0) -> 0
A8: ITEM0000007 | B8: ORD000005 | C8: PROD0092 | D8: 2 | E8: 20 | F8: 1316.7 | G8: FALSE | H8: =VLOOKUP(C8,Products!A:B,2,FALSE) -> Books & Stationery | I8: =IF(G8=TRUE,1,0) -> 0
A9: ITEM0000008 | B9: ORD000006 | C9: PROD0075 | D9: 1 | E9: 0 | F9: 1505.74 | G9: FALSE | H9: =VLOOKUP(C9,Products!A:B,2,FALSE) -> Sports & Fitness | I9: =IF(G9=TRUE,1,0) -> 0
A10: ITEM0000009 | B10: ORD000006 | C10: PROD0105 | D10: 2 | E10: 0 | F10: 1839.2 | G10: FALSE | H10: =VLOOKUP(C10,Products!A:B,2,FALSE) -> Books & Stationery | I10: =IF(G10=TRUE,1,0) -> 0
A11: ITEM0000010 | B11: ORD000007 | C11: PROD0021 | D11: 1 | E11: 10 | F11: 1544.36 | G11: FALSE | H11: =VLOOKUP(C11,Products!A:B,2,FALSE) -> Home & Kitchen | I11: =IF(G11=TRUE,1,0) -> 0
A12: ITEM0000011 | B12: ORD000007 | C12: PROD0005 | D12: 2 | E12: 15 | F12: 7956.25 | G12: FALSE | H12: =VLOOKUP(C12,Products!A:B,2,FALSE) -> Electronics | I12: =IF(G12=TRUE,1,0) -> 0
A13: ITEM0000012 | B13: ORD000008 | C13: PROD0103 | D13: 2 | E13: 10 | F13: 1726.58 | G13: FALSE | H13: =VLOOKUP(C13,Products!A:B,2,FALSE) -> Books & Stationery | I13: =IF(G13=TRUE,1,0) -> 0
... A16944: ITEM0016943 | B16944: ORD009000 | C16944: PROD0027 | D16944: 1 | E16944: 20 | F16944: 624.41 | G16944: FALSE | H16944: =VLOOKUP(C16944,Products!A:B,2,FALSE) -> Home & Kitchen | I16944: =IF(G16944=TRUE,1,0) -> 0
I16945: =IF(G16945=TRUE,1,0) -> 0
I16946: =IF(G16946=TRUE,1,0) -> 0
I16947: =IF(G16947=TRUE,1,0) -> 0
I16948: =IF(G16948=TRUE,1,0) -> 0

Sheet Region Analysis
A3: Row Labels | B3: Sum of order_total
A4: Central | B4: 7139192.3
A5: East | B5: 7506480.8
A6: North | B6: 10512376
A7: South | B7: 8843648.1
A8: West | B8: 7575470.9
A9: Grand Total | B9: 41577168

Sheet Payment Methods
A3: Row Labels | B3: Count of order_id
B4: 90
A5: Cash on Delivery | B5: 1349
A6: Credit Card | B6: 1670
A7: Debit Card | B7: 1287
A8: Net Banking | B8: 877
A9: UPI | B9: 3772
A10: Grand Total | B10: 9045

Sheet Order
A1: order_id | B1: customer_id | C1: order_date | D1: region | E1: payment_method | F1: order_total | G1: total_discount | H1: is_returned
A2: ORD000001 | B2: CUST00732 | C2: 45856 | D2: West | E2: Credit Card | F2: 1072.86 | G2: 119.21 | H2: FALSE
A3: ORD000002 | B3: CUST00076 | C3: 45927 | D3: West | E3: UPI | F3: 834.98 | G3: 92.78 | H3: FALSE
A4: ORD000003 | B4: CUST00089 | C4: 45427 | D4: Central | E4: Cash on Delivery | F4: 3460.58 | G4: 266.92 | H4: TRUE
A5: ORD000004 | B5: CUST01044 | C5: 45933 | D5: East | E5: UPI | F5: 1914.83 | G5: 0 | H5: FALSE
A6: ORD000005 | B6: CUST00137 | C6: 45701 | D6: East | E6: Cash on Delivery | F6: 1316.7 | G6: 329.18 | H6: FALSE
A7: ORD000006 | B7: CUST00404 | C7: 45938 | D7: West | E7: Cash on Delivery | F7: 3344.94 | G7: 0 | H7: FALSE
A8: ORD000007 | B8: CUST01050 | C8: 45612 | D8: North | E8: Cash on Delivery | F8: 9500.61 | G8: 1575.64 | H8: FALSE
A9: ORD000008 | B9: CUST00125 | C9: 45589 | D9: North | E9: UPI | F9: 1726.58 | G9: 191.84 | H9: FALSE
A10: ORD000009 | B10: CUST00129 | C10: 45970 | D10: North | E10: UPI | F10: 8506.46 | G10: 38.19 | H10: FALSE
A11: ORD000010 | B11: CUST00234 | C11: 45502 | D11: East | E11: Credit Card | F11: 571.28 | G11: 63.48 | H11: FALSE
A12: ORD000011 | B12: CUST01181 | C12: 45938 | D12: Central | E12: Debit Card | F12: 3931.89 | G12: 635.42 | H12: TRUE
A13: ORD000012 | B13: CUST00408 | C13: 45644 | D13: North | E13: UPI | F13: 952.14 | G13: 0 | H13: FALSE
... A83: ORD000082 | B83: CUST01168 | C83: 45965 | D83: East | E83: UPI | F83: 8674.72 | G83: 703.85 | H83: FALSE
A84: ORD000083 | B84: CUST00471 | C84: 45586 | D84: North | F84: 890.87 | G84: 0 | H84: FALSE
A85: ORD000084 | B85: CUST01081 | C85: 45712 | D85: West | E85: UPI | F85: 14814.11 | G85: 784.35 | H85: FALSE
A86: ORD000085 | B86: CUST00640 | C86: 45347 | D86: South | E86: Credit Card | F86: 3677.11 | G86: 0 | H86: FALSE
A87: ORD000086 | B87: CUST00226 | C87: 45610 | D87: South | E87: UPI | F87: 1156.98 | G87: 0 | H87: FALSE
A88: ORD000087 | B88: CUST00560 | C88: 45932 | D88: East | E88: UPI | F88: 403.28 | G88: 21.22 | H88: FALSE
A89: ORD000088 | B89: CUST00705 | C89: 45912 | D89: North | E89: UPI | F89: 1846.47 | G89: 97.18 | H89: FALSE
A90: ORD000089 | B90: CUST00841 | C90: 45486 | D90: North | E90: Cash on Delivery | F90: 7727.43 | G90: 406.71 | H90: FALSE
A91: ORD000090 | B91: CUST00995 | C91: 45487 | D91: South | E91: Net Banking | F91: 1544.36 | G91: 171.6 | H91: FALSE
A92: ORD000091 | B92: CUST00265 | C92: 45921 | D92: Central | E92: Debit Card | F92: 1090.56 | G92: 0 | H92: FALSE
A93: ORD000092 | B93: CUST00772 | C93: 45977 | D93: Central | E93: UPI | F93: 3629.6 | G93: 198.88 | H93: FALSE
A94: ORD000093 | B94: CUST00715 | C94: 45385 | D94: South | E94: UPI | F94: 1742.68 | G94: 435.67 | H94: FALSE
A95: ORD000094 | B95: CUST00862 | C95: 45621 | D95: South | E95: Credit Card | F95: 2837.44 | G95: 0 | H95: FALSE
A96: ORD000095 | B96: CUST00834 | C96: 45570 | D96: North | E96: Cash on Delivery | F96: 3547.27 | G96: 0 | H96: FALSE
... A255: ORD000254 | B255: CUST00220 | C255: 45599 | D255: Central | E255: Debit Card | F255: 142.1 | G255: 7.48 | H255: FALSE
A256: ORD000255 | B256: CUST01084 | C256: 45854 | D256: Central | F256: 822.94 | G256: 0 | H256: FALSE
A257: ORD000256 | B257: CUST01120 | C257: 45891 | D257: North | E257: UPI | F257: 8289 | G257: 1462.77 | H257: FALSE
A258: ORD000257 | B258: CUST00621 | C258: 45403 | D258: North | E258: Credit Card | F258: 1589.64 | G258: 176.63 | H258: FALSE
A259: ORD000258 | B259: CUST00453 | C259: 45292 | D259: South | E259: Debit Card | F259: 4718.07 | G259: 524.23 | H259: FALSE
A260: ORD000259 | B260: CUST00655 | C260: 45844 | D260: South | E260: Cash on Delivery | F260: 5364.11 | G260: 96.4 | H260: FALSE
A261: ORD000260 | B261: CUST00556 | C261: 45578 | D261: South | E261: UPI | F261: 4810.39 | G261: 271.53 | H261: FALSE
A262: ORD000261 | B262: CUST00110 | C262: 45505 | D262: North | E262: UPI | F262: 397.43 | G262: 99.36 | H262: FALSE
A263: ORD000262 | B263: CUST00329 | C263: 45306 | D263: South | E263: Credit Card | F263: 18883.16 | G263: 241.29 | H263: FALSE
A264: ORD000263 | B264: CUST00229 | C264: 45701 | D264: Central | E264: Credit Card | F264: 3442.55 | G264: 0 | H264: FALSE
A265: ORD000264 | B265: CUST00560 | C265: 45941 | D265: East | E265: UPI | F265: 3788.22 | G265: 199.38 | H265: FALSE
A266: ORD000265 | B266: CUST00083 | C266: 45990 | D266: South | E266: Credit Card | F266: 5224.75 | G266: 219.35 | H266: FALSE
A267: ORD000266 | B267: CUST00129 | C267: 45726 | D267: North | E267: Cash on Delivery | F267: 4332.39 | G267: 520.1 | H267: FALSE
A268: ORD000267 | B268: CUST00453 | C268: 45673 | D268: South | E268: Credit Card | F268: 3548.52 | G268: 242.23 | H268: FALSE
... A312: ORD000311 | B312: CUST00923 | C312: 45395 | D312: Central | E312: Credit Card | F312: 7617.59 | G312: 598.14 | H312: FALSE
A313: ORD000312 | B313: CUST01003 | C313: 45640 | D313: Central | F313: 4584.43 | G313: 241.29 | H313: FALSE
A314: ORD000313 | B314: CUST01000 | C314: 45742 | D314: South | E314: Cash on Delivery | F314: 9356.54 | G314: 913.11 | H314: TRUE
A315: ORD000314 | B315: CUST00005 | C315: 45703 | D315: NORTH | E315: Net Banking | F315: 13582.69 | G315: 3258.15 | H315: FALSE
A316: ORD000315 | B316: CUST00319 | C316: 45377 | D316: North | E316: UPI | F316: 13834.35 | G316: 354.73 | H316: FALSE
A317: ORD000316 | B317: CUST00509 | C317: 45353 | D317: Central | E317: Net Banking | F317: 5026.91 | G317: 533.07 | H317: FALSE
A318: ORD000317 | B318: CUST00246 | C318: 45393 | D318: Central | E318: Net Banking | F318: 993.58 | G318: 0 | H318: FALSE
A319: ORD000318 | B319: CUST00719 | C319: 45742 | D319: North | E319: UPI | F319: 3788.22 | G319: 199.38 | H319: FALSE
A320: ORD000319 | B320: CUST01098 | C320: 45706 | D320: North | E320: Debit Card | F320: 11031.33 | G320: 0 | H320: FALSE
A321: ORD000320 | B321: CUST00495 | C321: 45492 | D321: East | E321: UPI | F321: 3992.81 | G321: 183.86 | H321: FALSE
A322: ORD000321 | B322: CUST00735 | C322: 45785 | D322: South | E322: Credit Card | F322: 863.29 | G322: 95.92 | H322: FALSE
A323: ORD000322 | B323: CUST00954 | C323: 45924 | D323: Central | E323: Cash on Delivery | F323: 19177.21 | G323: 1443.88 | H323: TRUE
A324: ORD000323 | B324: CUST01048 | C324: 45337 | D324: North | E324: UPI | F324: 2180.05 | G324: 242.23 | H324: FALSE
A325: ORD000324 | B325: CUST00326 | C325: 45656 | D325: West | E325: Debit Card | F325: 8469.87 | G325: 877.94 | H325: FALSE
... A344: ORD000343 | B344: CUST00094 | C344: 45353 | D344: East | E344: UPI | F344: 4786.87 | G344: 108.7 | H344: TRUE
A345: ORD000344 | B345: CUST00173 | C345: 45880 | D345: East | F345: 7026.89 | G345: 1268.95 | H345: TRUE
A346: ORD000345 | B346: CUST00469 | C346: 45838 | D346: North | E346: Credit Card | F346: 9358.12 | G346: 492.53 | H346: FALSE
A347: ORD000346 | B347: CUST01024 | C347: 45567 | D347: Central | E347: Debit Card | F347: 3508.31 | G347: 0 | H347: FALSE
A348: ORD000347 | B348: CUST00515 | C348: 45816 | D348: North | E348: UPI | F348: 14431.96 | G348: 615.58 | H348: FALSE
A349: ORD000348 | B349: CUST00448 | C349: 45596 | D349: West | E349: Credit Card | F349: 11304.56 | G349: 709.45 | H349: FALSE
A350: ORD000349 | B350: CUST00549 | C350: 45871 | D350: East | E350: UPI | F350: 9541.05 | G350: 502.16 | H350: FALSE
A351: ORD000350 | B351: CUST00121 | C351: 45623 | D351: West | E351: UPI | F351: 3694.96 | G351: 410.55 | H351: FALSE
A352: ORD000351 | B352: CUST00191 | C352: 45604 | D352: North | E352: UPI | F352: 3694.96 | G352: 410.55 | H352: FALSE
A353: ORD000352 | B353: CUST00026 | C353: 45979 | D353: West | E353: Cash on Delivery | F353: 11364.66 | G353: 598.14 | H353: FALSE
A354: ORD000353 | B354: CUST00760 | C354: 45502 | D354: West | E354: Cash on Delivery | F354: 1586.7 | G354: 0 | H354: FALSE
A355: ORD000354 | B355: CUST01149 | C355: 45405 | D355: Central | E355: UPI | F355: 3534.64 | G355: 377.08 | H355: FALSE
A356: ORD000355 | B356: CUST00430 | C356: 45741 | D356: North | E356: UPI | F356: 578.49 | G356: 0 | H356: FALSE
A357: ORD000356 | B357: CUST00677 | C357: 45997 | D357: North | E357: Credit Card | F357: 9635.43 | G357: 1136.33 | H357: FALSE
... A373: ORD000372 | B373: CUST00534 | C373: 45617 | D373: East | E373: Cash on Delivery | F373: 2448.54 | G373: 324.95 | H373: FALSE
A374: ORD000373 | B374: CUST00480 | C374: 45794 | D374: East | F374: 3493.25 | G374: 183.86 | H374: FALSE
A375: ORD000374 | B375: CUST00518 | C375: 45357 | D375: West | E375: Debit Card | F375: 1532.89 | G375: 0 | H375: FALSE
A376: ORD000375 | B376: CUST00944 | C376: 45919 | D376: West | E376: Cash on Delivery | F376: 5119.84 | G376: 526.44 | H376: FALSE
A377: ORD000376 | B377: CUST00913 | C377: 45982 | D377: East | E377: Debit Card | F377: 17088.04 | G377: 301.42 | H377: TRUE
A378: ORD000377 | B378: CUST00586 | C378: 45794 | D378: South | E378: UPI | F378: 1146.22 | G378: 202.28 | H378: FALSE
A379: ORD000378 | B379: CUST00795 | C379: 45988 | D379: North | E379: Credit Card | F379: 556.67 | G379: 61.85 | H379: TRUE
A380: ORD000379 | B380: CUST00049 | C380: 45431 | D380: East | E380: Cash on Delivery | F380: 10204.49 | G380: 746.2 | H380: FALSE
A381: ORD000380 | B381: CUST00402 | C381: 45639 | D381: Central | E381: UPI | F381: 1274.78 | G381: 318.7 | H381: FALSE
A382: ORD000381 | B382: CUST00372 | C382: 45755 | D382: North | E382: Credit Card | F382: 2711.38 | G382: 0 | H382: FALSE
A383: ORD000382 | B383: CUST00233 | C383: 45739 | D383: East | E383: Cash on Delivery | F383: 920.74 | G383: 162.48 | H383: FALSE
A384: ORD000383 | B384: CUST00528 | C384: 45599 | D384: South | E384: UPI | F384: 2657.07 | G384: 664.27 | H384: FALSE
A385: ORD000384 | B385: CUST00038 | C385: 45570 | D385: North | E385: Cash on Delivery | F385: 4670.74 | G385: 193.87 | H385: FALSE
A386: ORD000385 | B386: CUST00876 | C386: 45410 | D386: North | E386: UPI | F386: 1593.48 | G386: 0 | H386: FALSE
... A598: ORD000597 | B598: CUST01026 | C598: 45510 | D598: East | E598: UPI | F598: 16176.88 | G598: 0 | H598: TRUE
A599: ORD000598 | B599: CUST00259 | C599: 45832 | D599: East | F599: 7177.68 | G599: 797.52 | H599: FALSE
A600: ORD000599 | B600: CUST00537 | C600: 45727 | D600: Central | E600: UPI | F600: 2969.83 | G600: 212.39 | H600: FALSE
A601: ORD000600 | B601: CUST00230 | C601: 45904 | D601: East | E601: Net Banking | F601: 4688.5 | G601: 145.29 | H601: FALSE
A602: ORD000601 | B602: CUST01089 | C602: 45858 | D602: Central | E602: Net Banking | F602: 3893.78 | G602: 483.18 | H602: FALSE
A603: ORD000602 | B603: CUST01000 | C603: 45762 | D603: South | E603: Credit Card | F603: 3047.33 | G603: 483.19 | H603: TRUE
A604: ORD000603 | B604: CUST00997 | C604: 45648 | D604: Central | E604: UPI | F604: 4124.23 | G604: 408.8 | H604: FALSE
A605: ORD000604 | B605: CUST00460 | C605: 45416 | D605: North | E605: Credit Card | F605: 288.91 | G605: 32.1 | H605: FALSE
A606: ORD000605 | B606: CUST00757 | C606: 45510 | D606: East | E606: Credit Card | F606: 3125.54 | G606: 551.57 | H606: FALSE
A607: ORD000606 | B607: CUST00375 | C607: 45607 | D607: North | E607: Debit Card | F607: 2455 | G607: 0 | H607: FALSE
A608: ORD000607 | B608: CUST00556 | C608: 45753 | D608: South | E608: UPI | F608: 10076.48 | G608: 540.36 | H608: FALSE
A609: ORD000608 | B609: CUST00868 | C609: 45672 | D609: North | E609: Debit Card | F609: 5154.43 | G609: 311.49 | H609: TRUE
A610: ORD000609 | B610: CUST00793 | C610: 45532 | D610: East | E610: Credit Card | F610: 1428.03 | G610: 158.67 | H610: FALSE
A611: ORD000610 | B611: CUST00646 | C611: 45299 | D611: Central | E611: UPI | F611: 1418.72 | G611: 0 | H611: FALSE
... A643: ORD000642 | B643: CUST00995 | C643: 45744 | D643: SOUTH | E643: UPI | F643: 496.79 | G643: 0 | H643: FALSE
A644: ORD000643 | B644: CUST00028 | C644: 45610 | D644: EAST | F644: 3500.87 | G644: 298.82 | H644: FALSE
A645: ORD000644 | B645: CUST00786 | C645: 45767 | D645: Central | E645: Debit Card | F645: 7375 | G645: 764.96 | H645: FALSE
...

Sheet Customers
A1: customer_id | B1: region | C1: city | D1: segment | E1: signup_date
A2: CUST00001 | B2: South | C2: Bengaluru | D2: Corporate | E2: 45444
A3: CUST00002 | B3: Central | C3: Raipur | D3: Small Business | E3: 44874
A4: CUST00003 | B4: West | C4: Ahmedabad | D4: Consumer | E4: 45401
A5: CUST00004 | B5: East | C5: Kolkata | D5: Consumer | E5: 45080
A6: CUST00005 | B6: North | C6: Lucknow | D6: Consumer | E6: 44767
A7: CUST00006 | B7: North | C7: Delhi | D7: Small Business | E7: 44936
A8: CUST00007 | B8: North | C8: Chandigarh | D8: Small Business | E8: 45012
A9: CUST00008 | B9: Central | C9: Indore | D9: Consumer | E9: 45187
A10: CUST00009 | B10: East | C10: Patna | D10: Consumer | E10: 45345
A11: CUST00010 | B11: West | C11: Surat | D11: Consumer | E11: 45156
A12: CUST00011 | B12: North | C12: Lucknow | D12: Small Business | E12: 44740
A13: CUST00012 | B13: Central | C13: Indore | D13: Small Business | E13: 44771
... A1201: CUST01200 | B1201: North | C1201: Delhi | D1201: Corporate | E1201: 44668
